{
  "hash": "4fa40f36",
  "browserHash": "a24520ae",
  "optimized": {
    "@vueuse/core": {
      "src": "../../../../node_modules/@vueuse/core/index.mjs",
      "file": "@vueuse_core.js",
      "fileHash": "c1dfed45",
      "needsInterop": false
    },
    "@vue/devtools-api": {
      "src": "../../../../node_modules/@vue/devtools-api/lib/esm/index.js",
      "file": "@vue_devtools-api.js",
      "fileHash": "585af2be",
      "needsInterop": false
    },
    "@vuepress/shared": {
      "src": "../../../../node_modules/@vuepress/shared/dist/index.js",
      "file": "@vuepress_shared.js",
      "fileHash": "90cc23b4",
      "needsInterop": false
    },
    "vue": {
      "src": "../../../../node_modules/vue/dist/vue.runtime.esm-bundler.js",
      "file": "vue.js",
      "fileHash": "c43b9ab5",
      "needsInterop": false
    },
    "vue-router": {
      "src": "../../../../node_modules/vue-router/dist/vue-router.esm-bundler.js",
      "file": "vue-router.js",
      "fileHash": "7995bc5c",
      "needsInterop": false
    }
  },
  "chunks": {
    "chunk-J4VLYDXT": {
      "file": "chunk-J4VLYDXT.js"
    },
    "chunk-PYXZ4PKZ": {
      "file": "chunk-PYXZ4PKZ.js"
    },
    "chunk-EVOPDU7K": {
      "file": "chunk-EVOPDU7K.js"
    }
  }
}